grammarinator/__init__.py
grammarinator/cli.py
grammarinator/decode.py
grammarinator/generate.py
grammarinator/parse.py
grammarinator/pkgdata.py
grammarinator/process.py
grammarinator/py.typed
grammarinator/runtime/__init__.py
grammarinator/runtime/default_model.py
grammarinator/runtime/dispatching_listener.py
grammarinator/runtime/dispatching_model.py
grammarinator/runtime/generator.py
grammarinator/runtime/listener.py
grammarinator/runtime/model.py
grammarinator/runtime/population.py
grammarinator/runtime/rule.py
grammarinator/runtime/serializer.py
grammarinator/runtime/weighted_model.py
grammarinator/tool/__init__.py
grammarinator/tool/file_population.py
grammarinator/tool/generator.py
grammarinator/tool/parser.py
grammarinator/tool/processor.py
grammarinator/tool/tree_codec.py
grammarinator/tool/fbs/FBRule_generated.py
grammarinator/tool/fbs/__init__.py
grammarinator/tool/g4/ANTLRv4Lexer.py
grammarinator/tool/g4/ANTLRv4Parser.py
grammarinator/tool/g4/LexerAdaptor.py
grammarinator/tool/g4/__init__.py
grammarinator/tool/resources/codegen/GeneratorTemplate.hpp.jinja
grammarinator/tool/resources/codegen/GeneratorTemplate.py.jinja
grammarinator/tool/resources/fbs/FBRule.fbs
grammarinator/tool/resources/g4/ANTLRv4Lexer.g4
grammarinator/tool/resources/g4/ANTLRv4Parser.g4
grammarinator/tool/resources/g4/LexBasic.g4
grammarinator-26.1.dist-info/licenses/LICENSE.rst
grammarinator-26.1.dist-info/METADATA
grammarinator-26.1.dist-info/WHEEL
grammarinator-26.1.dist-info/entry_points.txt
grammarinator-26.1.dist-info/top_level.txt
grammarinator-26.1.dist-info/RECORD
