Metadata-Version: 2.4
Name: grammarinator
Version: 26.1
Summary: Grammarinator: Grammar-based Random Test Generator
Home-page: https://github.com/renatahodovan/grammarinator
Author: Renata Hodovan, Akos Kiss
Author-email: hodovan@inf.u-szeged.hu, akiss@inf.u-szeged.hu
License-Expression: BSD-3-Clause
Platform: any
Classifier: Intended Audience :: Developers
Classifier: Operating System :: OS Independent
Classifier: Programming Language :: Python
Classifier: Programming Language :: Python :: 3
Classifier: Programming Language :: Python :: 3.10
Classifier: Programming Language :: Python :: 3.11
Classifier: Programming Language :: Python :: 3.12
Classifier: Programming Language :: Python :: 3.13
Classifier: Programming Language :: Python :: 3.14
Classifier: Topic :: Software Development :: Code Generators
Classifier: Topic :: Software Development :: Testing
Classifier: Typing :: Typed
Requires-Python: >=3.10
License-File: LICENSE.rst
Requires-Dist: antlerinator>=1!3.0.0
Requires-Dist: antlr4-python3-runtime==4.13.2
Requires-Dist: autopep8
Requires-Dist: enlighten
Requires-Dist: flatbuffers==25.9.23
Requires-Dist: inators
Requires-Dist: jinja2
Requires-Dist: regex
Requires-Dist: xxhash
Dynamic: license-file
Dynamic: license-expression
